find_conflicting_branches/__init__.py
find_conflicting_branches/lib.py
find_conflicting_branches-1.0.1.data/scripts/find_conflicting_branches
find_conflicting_branches-1.0.1.dist-info/METADATA
find_conflicting_branches-1.0.1.dist-info/RECORD
find_conflicting_branches-1.0.1.dist-info/WHEEL
find_conflicting_branches-1.0.1.dist-info/top_level.txt
